{"partition_key":"VGLLUD","PNR":{"PNRCreateDate":"2018-11-09","POSAgtDutyCode":"5","PNRPax":[{"FirstName_s":"nicole","SourceNameFieldId":"4","FirstName":"NICOLE","PNRPaxTrvlDoc":[{"GenderCode":"M","TrvlDocTypeCode":"DB","HostDesigIndicator":"true","NonPrimaryDocHolderIndicator":"false","FirstName":"NICOLE","NumberInParty":"1","SourcePaxTrvlDocId":"14","LastName_s":"harlander","FirstName_s":"nicole","DOB":"1975-04-04","DocSourceTypeCode":"DOCS","LastName":"HARLANDER","TrvlDocStatusCode":"HK"}],"WithInftIndicator":"false","PsgrSeqID":"1","LastName":"HARLANDER","PaxNameNumber":"01.01","LastName_s":"harlander","IsExtraSeatIndicator":"false","IsInftIndicator":"false"},{"FirstName_s":"andrea","SourceNameFieldId":"5","FirstName":"ANDREA","PNRPaxTrvlDoc":[{"GenderCode":"F","TrvlDocTypeCode":"DB","HostDesigIndicator":"true","NonPrimaryDocHolderIndicator":"false","FirstName":"ANDREA","NumberInParty":"1","SourcePaxTrvlDocId":"15","LastName_s":"harlander","FirstName_s":"andrea","DOB":"1980-04-28","DocSourceTypeCode":"DOCS","LastName":"HARLANDER","TrvlDocStatusCode":"HK"}],"WithInftIndicator":"false","PsgrSeqID":"2","LastName":"HARLANDER","PaxNameNumber":"02.01","LastName_s":"harlander","IsExtraSeatIndicator":"false","IsInftIndicator":"false"},{"FirstName_s":"bita","SourceNameFieldId":"6","FirstName":"BITA","PNRPaxTrvlDoc":[{"GenderCode":"F","TrvlDocTypeCode":"DB","HostDesigIndicator":"true","NonPrimaryDocHolderIndicator":"false","FirstName":"BITA","NumberInParty":"1","SourcePaxTrvlDocId":"16","LastName_s":"harlander","FirstName_s":"bita","DOB":"1975-12-21","DocSourceTypeCode":"DOCS","LastName":"HARLANDER","TrvlDocStatusCode":"HK"}],"WithInftIndicator":"false","PsgrSeqID":"3","LastName":"HARLANDER","PaxNameNumber":"03.01","LastName_s":"harlander","IsExtraSeatIndicator":"false","IsInftIndicator":"false"},{"FirstName_s":"cameron","SourceNameFieldId":"7","FirstName":"CAMERON","PNRPaxTrvlDoc":[{"GenderCode":"F","TrvlDocTypeCode":"DB","HostDesigIndicator":"true","NonPrimaryDocHolderIndicator":"false","FirstName":"CAMERON","NumberInParty":"1","SourcePaxTrvlDocId":"17","LastName_s":"harlander","FirstName_s":"cameron","DOB":"1980-12-28","DocSourceTypeCode":"DOCS","LastName":"HARLANDER","TrvlDocStatusCode":"HK"}],"WithInftIndicator":"false","PsgrSeqID":"4","LastName":"HARLANDER","PaxNameNumber":"04.01","LastName_s":"harlander","IsExtraSeatIndicator":"false","IsInftIndicator":"false"}],"PNRLinedAddr":[{"PNRAddrContactPurposeCode":"CCADDRVFY","PNRAddrLine3":"ORLANDO, FL","PNRAddrLine4":"32827","PNRAddrLine1":"NICOLE HARLANDER","PNRAddrLine2":"8265 HANGER BLVD"}],"NumberInParty":"4","FirstFlightDepLocalDateTime":"2018-11-21T18:55:00","POSAirlineVendorId":"XYZ","SourceSystemId":"Sabre","PNRLastUpdateUTCDateTime":"2018-11-09T19:24:37","EventSubType":"|Updated","PNRCreateUTCDateTime":"2018-11-09T19:24:00","PNREmail":[{"SourcePNREmailId":"12","PNREmailAddr":"s3c@jetblue.com"}],"EventId":"20181109142439.VGLLUD.2","EventCreationTimeStamp":"2018-11-09T14:24:39.724-05:00","POSPseudoCityCode":"MCO","ChangeIndicator":{"Value":"PNR","Name":"PNR"},"OriginalResCreateUTCDateTime":"2018-11-09T19:24:00","LastFlightArrLocalDateTime":"2018-11-21T21:25:00","PNRTktInfo":[{"TktInfoType":"TKTD","TktgFreeText":"T-09NOV-MCO5E99"},{"TktInfoType":"ETKTNBR","TktgFreeText":"TE 2792107853136 HARLA/N MCO5E99 1424/09NOV"},{"TktInfoType":"ETKTNBR","TktgFreeText":"TE 2792107853137 HARLA/A MCO5E99 1424/09NOV"},{"TktInfoType":"ETKTNBR","TktgFreeText":"TE 2792107853138 HARLA/B MCO5E99 1424/09NOV"},{"TktInfoType":"ETKTNBR","TktgFreeText":"TE 2792107853139 HARLA/C MCO5E99 1424/09NOV"},{"TktInfoType":"TKTDETAIL","PaxPartialName_s":"harla/n","TktNumber":"2792107853136","TktdLocalDateTime":"2018-11-08T14:24:00","PaxPartialName":"HARLA/N","TktgAgtDutyCode":"5","TktgFreeText":"TE 2792107853136 HARLA/N MCO5E99 1424/09NOV","TktgAgtSine":"E99","PaxNameNumber":"01.01","TktgAgtPseudoCityCode":"MCO","TktgTransactionTypeCode":"TE"},{"TktInfoType":"TKTDETAIL","PaxPartialName_s":"harla/a","TktNumber":"2792107853137","TktdLocalDateTime":"2018-11-08T14:24:00","PaxPartialName":"HARLA/A","TktgAgtDutyCode":"5","TktgFreeText":"TE 2792107853137 HARLA/A MCO5E99 1424/09NOV","TktgAgtSine":"E99","PaxNameNumber":"02.01","TktgAgtPseudoCityCode":"MCO","TktgTransactionTypeCode":"TE"},{"TktInfoType":"TKTDETAIL","PaxPartialName_s":"harla/b","TktNumber":"2792107853138","TktdLocalDateTime":"2018-11-08T14:24:00","PaxPartialName":"HARLA/B","TktgAgtDutyCode":"5","TktgFreeText":"TE 2792107853138 HARLA/B MCO5E99 1424/09NOV","TktgAgtSine":"E99","PaxNameNumber":"03.01","TktgAgtPseudoCityCode":"MCO","TktgTransactionTypeCode":"TE"},{"TktInfoType":"TKTDETAIL","PaxPartialName_s":"harla/c","TktNumber":"2792107853139","TktdLocalDateTime":"2018-11-08T14:24:00","PaxPartialName":"HARLA/C","TktgAgtDutyCode":"5","TktgFreeText":"TE 2792107853139 HARLA/C MCO5E99 1424/09NOV","TktgAgtSine":"E99","PaxNameNumber":"04.01","TktgAgtPseudoCityCode":"MCO","TktgTransactionTypeCode":"TE"}],"NumberOfInfants":"0","PNRState":[{"Value":"Ticketed"}],"DocumentType":"PNR","PNRSSR":[{"SSRFreeText":"B6 HK1 MCOJFK3122E21NOV/2792107853136C1","HostDesigIndicator":"true","SSRCode":"TKNE","TktNumber":"2792107853136","SSRStatusCode":"HK","SourceSSRId":"19","PaxNameNumber":"01.01","PNRItinAirSegNumber":"1","SSRFullText":"TKNE B6 HK1 MCOJFK3122E21NOV/2792107853136C1","SSRNumberInParty":"1","ServiceProviderCarrierCode":"XYZ"},{"SSRFreeText":"B6 HK1 MCOJFK3122E21NOV/2792107853137C1","HostDesigIndicator":"true","SSRCode":"TKNE","TktNumber":"2792107853137","SSRStatusCode":"HK","SourceSSRId":"21","PaxNameNumber":"02.01","PNRItinAirSegNumber":"1","SSRFullText":"TKNE B6 HK1 MCOJFK3122E21NOV/2792107853137C1","SSRNumberInParty":"1","ServiceProviderCarrierCode":"XYZ"},{"SSRFreeText":"B6 HK1 MCOJFK3122E21NOV/2792107853138C1","HostDesigIndicator":"true","SSRCode":"TKNE","TktNumber":"2792107853138","SSRStatusCode":"HK","SourceSSRId":"23","PaxNameNumber":"03.01","PNRItinAirSegNumber":"1","SSRFullText":"TKNE B6 HK1 MCOJFK3122E21NOV/2792107853138C1","SSRNumberInParty":"1","ServiceProviderCarrierCode":"XYZ"},{"SSRFreeText":"B6 HK1 MCOJFK3122E21NOV/2792107853139C1","HostDesigIndicator":"true","SSRCode":"TKNE","TktNumber":"2792107853139","SSRStatusCode":"HK","SourceSSRId":"25","PaxNameNumber":"04.01","PNRItinAirSegNumber":"1","SSRFullText":"TKNE B6 HK1 MCOJFK3122E21NOV/2792107853139C1","SSRNumberInParty":"1","ServiceProviderCarrierCode":"XYZ"}],"NumberInSeg":"4","DataIndicator":{"Value":"PNR","Name":"PNR"},"POSAgtSine":"E99","PNRPhone":[{"PNRPhoneNumber":"407-812-2000-S NICOLE","PNRPhoneCityCode":"MCO","PNRPhoneCityCode_s":"MCO","PNRPhoneContactPurposeCode":"PNR","SourcePNRPhoneId":"13","PNRPhoneNumber_s":"4078122000SNICOLE"}],"PNRRecordLocator":"VGLLUD","SourcePNRUpdateSeqNumber":"2","PNRPurgeDate":"2018-12-21","PNRItinAirSeg":[{"SourceSegAssocId":"2","PNRItinAirSegOriginAirportCode":"MCO","NumberInPNRItinAirSeg":"4","PNRItinAirSegMarketingBookingClass":"E","PNRItinAirSegMarketingCarrierCode":"XYZ","PNRItinAirSegArrLocalDateTime":"2018-11-21T21:25:00","PNRItinAirSegMarketingFlightNumber":"3122","PNRItinAirSegFlightNumber":"3122","CabinCode":"Y","PNRItinAirSegOperatingCarrierCode":"XYZ","HasInboundConxIndicator":"false","PNRItinAirSegStatusCode":"HK","HasOutbndConxIndicator":"false","PNRItinAirSegOperatingFlightNumber":"3122","PNRItinAirSegDepLocalDateTime":"2018-11-21T18:55:00","PNRItinAirSegDestAirportCode":"JFK","PNRItinAirSegBookingClass":"E","InsertdBySchChangeIndicator":"false","SourceSegId":"3","PNRItinAirSegOperatingBookingClass":"E","EtktEligblIndicator":"true","PNRItinAirSegNumber":"1","EqpmtType":"320"}],"POSCtryCode":"US"},"id":"VGLLUD_2018-11-09_PNR"}